fenicio/__init__.py
fenicio/_etc.py
fenicio/client.py
fenicio/orders.py
fenicio/request.py
fenicio/url.py
fenicio/functionals/__init__.py
fenicio/functionals/collect_orders.py
fenicio-0.1.1.dist-info/LICENSE
fenicio-0.1.1.dist-info/METADATA
fenicio-0.1.1.dist-info/WHEEL
fenicio-0.1.1.dist-info/top_level.txt
fenicio-0.1.1.dist-info/RECORD
